{
  "id": "majid-vaezi",
  "firstName": {
    "fa": "مجید",
    "en": "Majid"
  },
  "lastName": {
    "fa": "واعظی",
    "en": "Vaezi"
  },
  "age": null,
  "birthDate": null,
  "deathDate": "2026-01-08",
  "causeOfDeath": {
    "fa": "شلیک مستقیم نیروهای حکومتی در جریان اعتراضات",
    "en": "Killed by direct gunfire from government forces during protests"
  },
  "incidentDate": "2026-01-08",
  "location": {
    "city": "Tehran",
    "country": "Iran"
  },
  "status": "killed",
  "description": {
    "fa": "مجید واعظی، شهروند گیلک اهل لنگرود، روز پنجشنبه ۱۸ دی‌ماه ۱۴۰۴ در حالی که دخترش را در آغوش داشت، در یکی از خیابان‌های تهران با شلیک مستقیم نیروهای حکومتی کشته شد.",
    "en": "Majid Vaezi, a Gilaki citizen from Langarud, was killed on Thursday, January 8, 2026 in Tehran while holding his daughter, after being shot directly by government forces during protests."
  },
  "events": [
    "2025-2026-iran-protests"
  ],
  "images": [],
  "links": [
    {
      "url": "https://hengaw.net/fa/news/2026/01/article-95",
      "title": "Hengaw report on the killing of Majid Vaezi",
      "type": "news"
    }
  ],
  "verified": true,
  "published": true
}
