{
  "id": "meysam-yaghoubi",
  "firstName": {
    "fa": "میثم",
    "en": "Meysam"
  },
  "lastName": {
    "fa": "یعقوبی",
    "en": "Yaghoubi"
  },
  "age": 42,
  "birthDate": null,
  "deathDate": "2026-01-10",
  "causeOfDeath": {
    "fa": "اصابت گلوله به ناحیه قلب توسط نیروهای حکومت در جریان اعتراضات",
    "en": "Killed by a gunshot to the heart fired by government forces during protests"
  },
  "incidentDate": "2026-01-10",
  "location": {
    "city": "Lahijan",
    "country": "Iran"
  },
  "status": "killed",
  "description": {
    "fa": "میثم یعقوبی، ۴۲ ساله و شهروند گیلک اهل لاهیجان، روز ۲۰ دی‌ماه ۱۴۰۴ در جریان اعتراضات مردمی و درگیری‌های خیابانی در یکی از کوچه‌های این شهر هدف شلیک نیروهای حکومت جمهوری اسلامی ایران قرار گرفت و بر اثر اصابت گلوله به ناحیه قلب جان باخت.",
    "en": "Meysam Yaghoubi, 42, a Gilak citizen from Lahijan, was shot by Islamic Republic government forces during street protests on January 10, 2026, and died after being struck in the heart."
  },
  "events": [
    "2025-2026-iran-protests"
  ],
  "images": [
    "images/people/meysam-yaghoubi/profile.jpeg"
  ],
  "links": [
    {
      "url": "https://x.com/HyrcaniHRM/status/2011783582935622044",
      "title": "Report on the killing of Meysam Yaghoubi",
      "type": "social_media"
    }
  ],
  "verified": true,
  "published": true
}
